{
  "config": {
    "step": {
      "user": {
        "title": "TruLight BLE Controller",
        "description": "Configure a TruLight BLE LED controller via ESPHome proxy.\n\nYou need an ESP32 running the TruLight BLE proxy ESPHome firmware that exposes a text command entity and power on/off button entities.",
        "data": {
          "name": "Name",
          "command_entity": "ESPHome Command Entity (text.xxx)",
          "power_on_entity": "ESPHome Power On Entity (button.xxx)",
          "power_off_entity": "ESPHome Power Off Entity (button.xxx)"
        },
        "data_description": {
          "name": "A friendly name for this TruLight controller (e.g., Backyard, Front)",
          "command_entity": "The ESPHome text entity that accepts hex commands",
          "power_on_entity": "The ESPHome button entity that turns the controller on",
          "power_off_entity": "The ESPHome button entity that turns the controller off"
        }
      }
    },
    "error": {
      "entity_not_found": "Entity not found. Make sure the ESPHome device is online.",
      "invalid_text_entity": "Must be a text entity (text.xxx)",
      "invalid_button_entity": "Must be a button entity (button.xxx)"
    },
    "abort": {
      "already_configured": "This TruLight controller is already configured."
    }
  }
}
